setup.py
wordpress_reader/__init__.py
wordpress_reader/objects.py
wordpress_reader.egg-info/PKG-INFO
wordpress_reader.egg-info/SOURCES.txt
wordpress_reader.egg-info/dependency_links.txt
wordpress_reader.egg-info/requires.txt
wordpress_reader.egg-info/top_level.txt