Metadata-Version: 1.0
Name: wordpress-reader
Version: 0.3.0
Summary: A Python library to pull data out of Wordpress.
Home-page: https://bitbucket.org/onetouchteam/wordpress-reader
Author: onetouchteam.com
Author-email: dev@onetouchteam.com
License: BSD
Platform: UNKNOWN
